personal_finance/__init__.py
personal_finance/main.py
personal_finance_cli-0.0.1.dist-info/licenses/LICENSE
personal_finance_cli-0.0.1.dist-info/METADATA
personal_finance_cli-0.0.1.dist-info/WHEEL
personal_finance_cli-0.0.1.dist-info/entry_points.txt
personal_finance_cli-0.0.1.dist-info/top_level.txt
personal_finance_cli-0.0.1.dist-info/RECORD
