Metadata-Version: 2.4
Name: personal_finance_cli
Version: 0.0.1
Summary: A simple personal finance CLI manager
Author-email: Rupneel <rupneel@example.com>
Classifier: Programming Language :: Python :: 3
Classifier: License :: OSI Approved :: MIT License
Classifier: Operating System :: OS Independent
Requires-Python: >=3.7
License-File: LICENSE
Dynamic: license-file
